<?xml version="1.0" encoding="UTF-8"?>
<SchemaFile xmlns="" xmlns:xs="http://www.w3.org/2001/XMLSchema" xmlns:xsi="http://www.w3.org/2001/XMLSchema-instance">
	<dataCompositionSchema xmlns="http://v8.1c.ru/8.1/data-composition-system/schema">
		<dataSource>
			<name>ИсточникДанных1</name>
			<dataSourceType>Local</dataSourceType>
		</dataSource>
		<dataSet xsi:type="DataSetObject">
			<name>ДанныеИсточника</name>
			<field xsi:type="DataSetFieldField">
				<dataPath>Продукция</dataPath>
				<field>Продукция</field>
				<title xmlns:d5p1="http://v8.1c.ru/8.1/data/core" xsi:type="d5p1:LocalStringType">
					<d5p1:item>
						<d5p1:lang>ru</d5p1:lang>
						<d5p1:content>Продукция</d5p1:content>
					</d5p1:item>
				</title>
				<appearance/>
			</field>
			<field xsi:type="DataSetFieldField">
				<dataPath>ХарактеристикаПродукции</dataPath>
				<field>ХарактеристикаПродукции</field>
				<title xmlns:d5p1="http://v8.1c.ru/8.1/data/core" xsi:type="d5p1:LocalStringType">
					<d5p1:item>
						<d5p1:lang>ru</d5p1:lang>
						<d5p1:content>Характеристика продукции</d5p1:content>
					</d5p1:item>
				</title>
				<appearance/>
			</field>
			<field xsi:type="DataSetFieldField">
				<dataPath>ЗаказПокупателя</dataPath>
				<field>ЗаказПокупателя</field>
				<title xmlns:d5p1="http://v8.1c.ru/8.1/data/core" xsi:type="d5p1:LocalStringType">
					<d5p1:item>
						<d5p1:lang>ru</d5p1:lang>
						<d5p1:content>Заказ покупателя</d5p1:content>
					</d5p1:item>
				</title>
				<appearance/>
			</field>
			<field xsi:type="DataSetFieldField">
				<dataPath>Количество</dataPath>
				<field>Количество</field>
				<title xmlns:d5p1="http://v8.1c.ru/8.1/data/core" xsi:type="d5p1:LocalStringType">
					<d5p1:item>
						<d5p1:lang>ru</d5p1:lang>
						<d5p1:content>Количество</d5p1:content>
					</d5p1:item>
				</title>
				<valueType>
					<Type xmlns="http://v8.1c.ru/8.1/data/core">xs:decimal</Type>
					<NumberQualifiers xmlns="http://v8.1c.ru/8.1/data/core">
						<Digits>0</Digits>
						<FractionDigits>0</FractionDigits>
						<AllowedSign>Any</AllowedSign>
					</NumberQualifiers>
				</valueType>
				<appearance>
					<item xmlns="http://v8.1c.ru/8.1/data-composition-system/core" xmlns:dcsset="http://v8.1c.ru/8.1/data-composition-system/settings" xsi:type="dcsset:SettingsParameterValue">
						<parameter>Формат</parameter>
						<value xmlns:d7p1="http://v8.1c.ru/8.1/data/core" xsi:type="d7p1:LocalStringType">
							<d7p1:item>
								<d7p1:lang>ru</d7p1:lang>
								<d7p1:content>ЧДЦ=2</d7p1:content>
							</d7p1:item>
						</value>
					</item>
				</appearance>
			</field>
			<field xsi:type="DataSetFieldField">
				<dataPath>СуммаСНДС</dataPath>
				<field>СуммаСНДС</field>
				<title xmlns:d5p1="http://v8.1c.ru/8.1/data/core" xsi:type="d5p1:LocalStringType">
					<d5p1:item>
						<d5p1:lang>ru</d5p1:lang>
						<d5p1:content>Сумма СНДС</d5p1:content>
					</d5p1:item>
				</title>
				<valueType>
					<Type xmlns="http://v8.1c.ru/8.1/data/core">xs:decimal</Type>
					<NumberQualifiers xmlns="http://v8.1c.ru/8.1/data/core">
						<Digits>0</Digits>
						<FractionDigits>0</FractionDigits>
						<AllowedSign>Any</AllowedSign>
					</NumberQualifiers>
				</valueType>
				<appearance>
					<item xmlns="http://v8.1c.ru/8.1/data-composition-system/core" xmlns:dcsset="http://v8.1c.ru/8.1/data-composition-system/settings" xsi:type="dcsset:SettingsParameterValue">
						<parameter>Формат</parameter>
						<value xmlns:d7p1="http://v8.1c.ru/8.1/data/core" xsi:type="d7p1:LocalStringType">
							<d7p1:item>
								<d7p1:lang>ru</d7p1:lang>
								<d7p1:content>ЧДЦ=2</d7p1:content>
							</d7p1:item>
						</value>
					</item>
				</appearance>
			</field>
			<field xsi:type="DataSetFieldField">
				<dataPath>НДС</dataPath>
				<field>НДС</field>
				<title xmlns:d5p1="http://v8.1c.ru/8.1/data/core" xsi:type="d5p1:LocalStringType">
					<d5p1:item>
						<d5p1:lang>ru</d5p1:lang>
						<d5p1:content>НДС</d5p1:content>
					</d5p1:item>
				</title>
				<valueType>
					<Type xmlns="http://v8.1c.ru/8.1/data/core">xs:decimal</Type>
					<NumberQualifiers xmlns="http://v8.1c.ru/8.1/data/core">
						<Digits>0</Digits>
						<FractionDigits>0</FractionDigits>
						<AllowedSign>Any</AllowedSign>
					</NumberQualifiers>
				</valueType>
				<appearance>
					<item xmlns="http://v8.1c.ru/8.1/data-composition-system/core" xmlns:dcsset="http://v8.1c.ru/8.1/data-composition-system/settings" xsi:type="dcsset:SettingsParameterValue">
						<parameter>Формат</parameter>
						<value xmlns:d7p1="http://v8.1c.ru/8.1/data/core" xsi:type="d7p1:LocalStringType">
							<d7p1:item>
								<d7p1:lang>ru</d7p1:lang>
								<d7p1:content>ЧДЦ=2</d7p1:content>
							</d7p1:item>
						</value>
					</item>
				</appearance>
			</field>
			<field xsi:type="DataSetFieldField">
				<dataPath>СуммаБезНДС</dataPath>
				<field>СуммаБезНДС</field>
				<title xmlns:d5p1="http://v8.1c.ru/8.1/data/core" xsi:type="d5p1:LocalStringType">
					<d5p1:item>
						<d5p1:lang>ru</d5p1:lang>
						<d5p1:content>Сумма без НДС</d5p1:content>
					</d5p1:item>
				</title>
				<valueType>
					<Type xmlns="http://v8.1c.ru/8.1/data/core">xs:decimal</Type>
					<NumberQualifiers xmlns="http://v8.1c.ru/8.1/data/core">
						<Digits>0</Digits>
						<FractionDigits>0</FractionDigits>
						<AllowedSign>Any</AllowedSign>
					</NumberQualifiers>
				</valueType>
				<appearance>
					<item xmlns="http://v8.1c.ru/8.1/data-composition-system/core" xmlns:dcsset="http://v8.1c.ru/8.1/data-composition-system/settings" xsi:type="dcsset:SettingsParameterValue">
						<parameter>Формат</parameter>
						<value xmlns:d7p1="http://v8.1c.ru/8.1/data/core" xsi:type="d7p1:LocalStringType">
							<d7p1:item>
								<d7p1:lang>ru</d7p1:lang>
								<d7p1:content>ЧДЦ=2</d7p1:content>
							</d7p1:item>
						</value>
					</item>
				</appearance>
			</field>
			<field xsi:type="DataSetFieldField">
				<dataPath>СтоимостьЗатраты</dataPath>
				<field>СтоимостьЗатраты</field>
				<title xmlns:d5p1="http://v8.1c.ru/8.1/data/core" xsi:type="d5p1:LocalStringType">
					<d5p1:item>
						<d5p1:lang>ru</d5p1:lang>
						<d5p1:content>Стоимость затраты</d5p1:content>
					</d5p1:item>
				</title>
				<valueType>
					<Type xmlns="http://v8.1c.ru/8.1/data/core">xs:decimal</Type>
					<NumberQualifiers xmlns="http://v8.1c.ru/8.1/data/core">
						<Digits>0</Digits>
						<FractionDigits>0</FractionDigits>
						<AllowedSign>Any</AllowedSign>
					</NumberQualifiers>
				</valueType>
				<appearance>
					<item xmlns="http://v8.1c.ru/8.1/data-composition-system/core" xmlns:dcsset="http://v8.1c.ru/8.1/data-composition-system/settings" xsi:type="dcsset:SettingsParameterValue">
						<parameter>Формат</parameter>
						<value xmlns:d7p1="http://v8.1c.ru/8.1/data/core" xsi:type="d7p1:LocalStringType">
							<d7p1:item>
								<d7p1:lang>ru</d7p1:lang>
								<d7p1:content>ЧДЦ=2</d7p1:content>
							</d7p1:item>
						</value>
					</item>
				</appearance>
			</field>
			<field xsi:type="DataSetFieldField">
				<dataPath>Сумма26</dataPath>
				<field>Сумма26</field>
				<title xmlns:d5p1="http://v8.1c.ru/8.1/data/core" xsi:type="d5p1:LocalStringType">
					<d5p1:item>
						<d5p1:lang>ru</d5p1:lang>
						<d5p1:content>Сумма26</d5p1:content>
					</d5p1:item>
				</title>
				<valueType>
					<Type xmlns="http://v8.1c.ru/8.1/data/core">xs:decimal</Type>
					<NumberQualifiers xmlns="http://v8.1c.ru/8.1/data/core">
						<Digits>0</Digits>
						<FractionDigits>0</FractionDigits>
						<AllowedSign>Any</AllowedSign>
					</NumberQualifiers>
				</valueType>
				<appearance>
					<item xmlns="http://v8.1c.ru/8.1/data-composition-system/core" xmlns:dcsset="http://v8.1c.ru/8.1/data-composition-system/settings" xsi:type="dcsset:SettingsParameterValue">
						<parameter>Формат</parameter>
						<value xmlns:d7p1="http://v8.1c.ru/8.1/data/core" xsi:type="d7p1:LocalStringType">
							<d7p1:item>
								<d7p1:lang>ru</d7p1:lang>
								<d7p1:content>ЧДЦ=2</d7p1:content>
							</d7p1:item>
						</value>
					</item>
				</appearance>
			</field>
			<field xsi:type="DataSetFieldField">
				<dataPath>Сумма44</dataPath>
				<field>Сумма44</field>
				<title xmlns:d5p1="http://v8.1c.ru/8.1/data/core" xsi:type="d5p1:LocalStringType">
					<d5p1:item>
						<d5p1:lang>ru</d5p1:lang>
						<d5p1:content>Сумма44</d5p1:content>
					</d5p1:item>
				</title>
				<valueType>
					<Type xmlns="http://v8.1c.ru/8.1/data/core">xs:decimal</Type>
					<NumberQualifiers xmlns="http://v8.1c.ru/8.1/data/core">
						<Digits>0</Digits>
						<FractionDigits>0</FractionDigits>
						<AllowedSign>Any</AllowedSign>
					</NumberQualifiers>
				</valueType>
				<appearance>
					<item xmlns="http://v8.1c.ru/8.1/data-composition-system/core" xmlns:dcsset="http://v8.1c.ru/8.1/data-composition-system/settings" xsi:type="dcsset:SettingsParameterValue">
						<parameter>Формат</parameter>
						<value xmlns:d7p1="http://v8.1c.ru/8.1/data/core" xsi:type="d7p1:LocalStringType">
							<d7p1:item>
								<d7p1:lang>ru</d7p1:lang>
								<d7p1:content>ЧДЦ=2</d7p1:content>
							</d7p1:item>
						</value>
					</item>
				</appearance>
			</field>
			<field xsi:type="DataSetFieldField">
				<dataPath>ВсегоЗатрат</dataPath>
				<field>ВсегоЗатрат</field>
				<title xmlns:d5p1="http://v8.1c.ru/8.1/data/core" xsi:type="d5p1:LocalStringType">
					<d5p1:item>
						<d5p1:lang>ru</d5p1:lang>
						<d5p1:content>Всего затрат</d5p1:content>
					</d5p1:item>
				</title>
				<valueType>
					<Type xmlns="http://v8.1c.ru/8.1/data/core">xs:decimal</Type>
					<NumberQualifiers xmlns="http://v8.1c.ru/8.1/data/core">
						<Digits>0</Digits>
						<FractionDigits>0</FractionDigits>
						<AllowedSign>Any</AllowedSign>
					</NumberQualifiers>
				</valueType>
				<appearance>
					<item xmlns="http://v8.1c.ru/8.1/data-composition-system/core" xmlns:dcsset="http://v8.1c.ru/8.1/data-composition-system/settings" xsi:type="dcsset:SettingsParameterValue">
						<parameter>Формат</parameter>
						<value xmlns:d7p1="http://v8.1c.ru/8.1/data/core" xsi:type="d7p1:LocalStringType">
							<d7p1:item>
								<d7p1:lang>ru</d7p1:lang>
								<d7p1:content>ЧДЦ=2</d7p1:content>
							</d7p1:item>
						</value>
					</item>
				</appearance>
			</field>
			<field xsi:type="DataSetFieldField">
				<dataPath>ИтогоЗатрат</dataPath>
				<field>ИтогоЗатрат</field>
				<title xmlns:d5p1="http://v8.1c.ru/8.1/data/core" xsi:type="d5p1:LocalStringType">
					<d5p1:item>
						<d5p1:lang>ru</d5p1:lang>
						<d5p1:content>Итого затрат</d5p1:content>
					</d5p1:item>
				</title>
				<valueType>
					<Type xmlns="http://v8.1c.ru/8.1/data/core">xs:decimal</Type>
					<NumberQualifiers xmlns="http://v8.1c.ru/8.1/data/core">
						<Digits>0</Digits>
						<FractionDigits>0</FractionDigits>
						<AllowedSign>Any</AllowedSign>
					</NumberQualifiers>
				</valueType>
				<appearance>
					<item xmlns="http://v8.1c.ru/8.1/data-composition-system/core" xmlns:dcsset="http://v8.1c.ru/8.1/data-composition-system/settings" xsi:type="dcsset:SettingsParameterValue">
						<parameter>Формат</parameter>
						<value xmlns:d7p1="http://v8.1c.ru/8.1/data/core" xsi:type="d7p1:LocalStringType">
							<d7p1:item>
								<d7p1:lang>ru</d7p1:lang>
								<d7p1:content>ЧДЦ=2</d7p1:content>
							</d7p1:item>
						</value>
					</item>
				</appearance>
			</field>
			<field xsi:type="DataSetFieldField">
				<dataPath>Рентабельность</dataPath>
				<field>Рентабельность</field>
				<title xmlns:d5p1="http://v8.1c.ru/8.1/data/core" xsi:type="d5p1:LocalStringType">
					<d5p1:item>
						<d5p1:lang>ru</d5p1:lang>
						<d5p1:content>Рентабельность</d5p1:content>
					</d5p1:item>
				</title>
				<valueType>
					<Type xmlns="http://v8.1c.ru/8.1/data/core">xs:decimal</Type>
					<NumberQualifiers xmlns="http://v8.1c.ru/8.1/data/core">
						<Digits>0</Digits>
						<FractionDigits>0</FractionDigits>
						<AllowedSign>Any</AllowedSign>
					</NumberQualifiers>
				</valueType>
				<appearance>
					<item xmlns="http://v8.1c.ru/8.1/data-composition-system/core" xmlns:dcsset="http://v8.1c.ru/8.1/data-composition-system/settings" xsi:type="dcsset:SettingsParameterValue">
						<parameter>Формат</parameter>
						<value xmlns:d7p1="http://v8.1c.ru/8.1/data/core" xsi:type="d7p1:LocalStringType">
							<d7p1:item>
								<d7p1:lang>ru</d7p1:lang>
								<d7p1:content>ЧДЦ=2</d7p1:content>
							</d7p1:item>
						</value>
					</item>
				</appearance>
			</field>
			<field xsi:type="DataSetFieldField">
				<dataPath>Контрагент</dataPath>
				<field>Контрагент</field>
				<title xmlns:d5p1="http://v8.1c.ru/8.1/data/core" xsi:type="d5p1:LocalStringType">
					<d5p1:item>
						<d5p1:lang>ru</d5p1:lang>
						<d5p1:content>Контрагент</d5p1:content>
					</d5p1:item>
				</title>
				<valueType>
					<Type xmlns="http://v8.1c.ru/8.1/data/core" xmlns:d6p1="http://v8.1c.ru/8.1/data/enterprise/current-config">d6p1:CatalogRef.Контрагенты</Type>
				</valueType>
				<appearance/>
			</field>
			<field xsi:type="DataSetFieldField">
				<dataPath>Прибыль</dataPath>
				<field>Прибыль</field>
				<title xmlns:d5p1="http://v8.1c.ru/8.1/data/core" xsi:type="d5p1:LocalStringType">
					<d5p1:item>
						<d5p1:lang>ru</d5p1:lang>
						<d5p1:content>Прибыль</d5p1:content>
					</d5p1:item>
				</title>
				<valueType>
					<Type xmlns="http://v8.1c.ru/8.1/data/core">xs:decimal</Type>
					<NumberQualifiers xmlns="http://v8.1c.ru/8.1/data/core">
						<Digits>0</Digits>
						<FractionDigits>0</FractionDigits>
						<AllowedSign>Any</AllowedSign>
					</NumberQualifiers>
				</valueType>
				<appearance>
					<item xmlns="http://v8.1c.ru/8.1/data-composition-system/core" xmlns:dcsset="http://v8.1c.ru/8.1/data-composition-system/settings" xsi:type="dcsset:SettingsParameterValue">
						<parameter>Формат</parameter>
						<value xmlns:d7p1="http://v8.1c.ru/8.1/data/core" xsi:type="d7p1:LocalStringType">
							<d7p1:item>
								<d7p1:lang>ru</d7p1:lang>
								<d7p1:content>ЧДЦ=2</d7p1:content>
							</d7p1:item>
						</value>
					</item>
				</appearance>
			</field>
			<field xsi:type="DataSetFieldField">
				<dataPath>НоменклатурнаяГруппа</dataPath>
				<field>НоменклатурнаяГруппа</field>
				<title xmlns:d5p1="http://v8.1c.ru/8.1/data/core" xsi:type="d5p1:LocalStringType">
					<d5p1:item>
						<d5p1:lang>ru</d5p1:lang>
						<d5p1:content>Номенклатурная группа</d5p1:content>
					</d5p1:item>
				</title>
				<appearance/>
			</field>
			<field xsi:type="DataSetFieldField">
				<dataPath>Регистратор</dataPath>
				<field>Регистратор</field>
				<title xmlns:d5p1="http://v8.1c.ru/8.1/data/core" xsi:type="d5p1:LocalStringType">
					<d5p1:item>
						<d5p1:lang>ru</d5p1:lang>
						<d5p1:content>Регистратор</d5p1:content>
					</d5p1:item>
				</title>
				<valueType>
					<TypeSet xmlns="http://v8.1c.ru/8.1/data/core" xmlns:d6p1="http://v8.1c.ru/8.1/data/enterprise/current-config">d6p1:DocumentRef</TypeSet>
				</valueType>
				<appearance/>
			</field>
			<dataSource>ИсточникДанных1</dataSource>
			<objectName>ДанныеИсточника</objectName>
		</dataSet>
		<totalField>
			<dataPath>ВсегоЗатрат</dataPath>
			<expression>Сумма(ВсегоЗатрат)</expression>
		</totalField>
		<totalField>
			<dataPath>ИтогоЗатрат</dataPath>
			<expression>Сумма(ИтогоЗатрат)</expression>
		</totalField>
		<totalField>
			<dataPath>Количество</dataPath>
			<expression>Сумма(Количество)</expression>
		</totalField>
		<totalField>
			<dataPath>НДС</dataPath>
			<expression>Сумма(НДС)</expression>
		</totalField>
		<totalField>
			<dataPath>Рентабельность</dataPath>
			<expression>Среднее(Рентабельность)</expression>
		</totalField>
		<totalField>
			<dataPath>СтоимостьЗатраты</dataPath>
			<expression>Сумма(СтоимостьЗатраты)</expression>
		</totalField>
		<totalField>
			<dataPath>Сумма26</dataPath>
			<expression>Сумма(Сумма26)</expression>
		</totalField>
		<totalField>
			<dataPath>Сумма44</dataPath>
			<expression>Сумма(Сумма44)</expression>
		</totalField>
		<totalField>
			<dataPath>СуммаБезНДС</dataPath>
			<expression>Сумма(СуммаБезНДС)</expression>
		</totalField>
		<totalField>
			<dataPath>СуммаСНДС</dataPath>
			<expression>Сумма(СуммаСНДС)</expression>
		</totalField>
		<totalField>
			<dataPath>Прибыль</dataPath>
			<expression>Сумма(Прибыль)</expression>
		</totalField>
		<settingsVariant>
			<name xmlns="http://v8.1c.ru/8.1/data-composition-system/settings">Основной</name>
			<presentation xmlns="http://v8.1c.ru/8.1/data-composition-system/settings" xsi:type="xs:string">Основной</presentation>
		</settingsVariant>
	</dataCompositionSchema>
</SchemaFile>﻿<?xml version="1.0" encoding="UTF-8"?>
<Settings xmlns="http://v8.1c.ru/8.1/data-composition-system/settings" xmlns:dcscor="http://v8.1c.ru/8.1/data-composition-system/core" xmlns:style="http://v8.1c.ru/8.1/data/ui/style" xmlns:sys="http://v8.1c.ru/8.1/data/ui/fonts/system" xmlns:v8="http://v8.1c.ru/8.1/data/core" xmlns:v8ui="http://v8.1c.ru/8.1/data/ui" xmlns:web="http://v8.1c.ru/8.1/data/ui/colors/web" xmlns:win="http://v8.1c.ru/8.1/data/ui/colors/windows" xmlns:xs="http://www.w3.org/2001/XMLSchema" xmlns:xsi="http://www.w3.org/2001/XMLSchema-instance">
	<selection>
		<item xsi:type="SelectedItemField">
			<field>Контрагент</field>
		</item>
		<item xsi:type="SelectedItemField">
			<field>ЗаказПокупателя</field>
		</item>
		<item xsi:type="SelectedItemField">
			<field>Продукция</field>
		</item>
		<item xsi:type="SelectedItemField">
			<field>ХарактеристикаПродукции</field>
		</item>
		<item xsi:type="SelectedItemField">
			<field>Количество</field>
			<lwsTitle>
				<v8:item>
					<v8:lang>ru</v8:lang>
					<v8:content>Количество продукции</v8:content>
				</v8:item>
			</lwsTitle>
		</item>
		<item xsi:type="SelectedItemField">
			<field>СуммаСНДС</field>
			<lwsTitle>
				<v8:item>
					<v8:lang>ru</v8:lang>
					<v8:content>Сумма с НДС</v8:content>
				</v8:item>
			</lwsTitle>
		</item>
		<item xsi:type="SelectedItemField">
			<field>НДС</field>
		</item>
		<item xsi:type="SelectedItemField">
			<field>СуммаБезНДС</field>
			<lwsTitle>
				<v8:item>
					<v8:lang>ru</v8:lang>
					<v8:content>Сумма без НДС</v8:content>
				</v8:item>
			</lwsTitle>
		</item>
		<item xsi:type="SelectedItemField">
			<field>СтоимостьЗатраты</field>
			<lwsTitle>
				<v8:item>
					<v8:lang>ru</v8:lang>
					<v8:content>Себестоимость</v8:content>
				</v8:item>
			</lwsTitle>
		</item>
		<item xsi:type="SelectedItemField">
			<field>Сумма26</field>
			<lwsTitle>
				<v8:item>
					<v8:lang>ru</v8:lang>
					<v8:content>Сумма ОХР (26 счет)</v8:content>
				</v8:item>
			</lwsTitle>
		</item>
		<item xsi:type="SelectedItemField">
			<field>Сумма44</field>
			<lwsTitle>
				<v8:item>
					<v8:lang>ru</v8:lang>
					<v8:content>Сумма КР (44 счет)</v8:content>
				</v8:item>
			</lwsTitle>
		</item>
		<item xsi:type="SelectedItemField">
			<field>ВсегоЗатрат</field>
			<lwsTitle>
				<v8:item>
					<v8:lang>ru</v8:lang>
					<v8:content>Всего затрат</v8:content>
				</v8:item>
			</lwsTitle>
		</item>
		<item xsi:type="SelectedItemField">
			<field>Прибыль</field>
		</item>
		<item xsi:type="SelectedItemField">
			<field>Рентабельность</field>
			<lwsTitle>
				<v8:item>
					<v8:lang>ru</v8:lang>
					<v8:content>Рентабельность продукции</v8:content>
				</v8:item>
			</lwsTitle>
		</item>
	</selection>
	<outputParameters>
		<dcscor:item xsi:type="SettingsParameterValue">
			<dcscor:parameter>ГоризонтальноеРасположениеОбщихИтогов</dcscor:parameter>
			<dcscor:value xsi:type="dcscor:DataCompositionTotalPlacement">BeginAndEnd</dcscor:value>
		</dcscor:item>
		<dcscor:item xsi:type="SettingsParameterValue">
			<dcscor:parameter>ВертикальноеРасположениеОбщихИтогов</dcscor:parameter>
			<dcscor:value xsi:type="dcscor:DataCompositionTotalPlacement">BeginAndEnd</dcscor:value>
		</dcscor:item>
	</outputParameters>
	<item xsi:type="StructureItemGroup">
		<groupItems>
			<item xsi:type="GroupItemField">
				<field>Контрагент</field>
				<groupType>Items</groupType>
				<periodAdditionType>None</periodAdditionType>
				<periodAdditionBegin xsi:type="xs:dateTime">0001-01-01T00:00:00</periodAdditionBegin>
				<periodAdditionEnd xsi:type="xs:dateTime">0001-01-01T00:00:00</periodAdditionEnd>
			</item>
		</groupItems>
		<order>
			<item xsi:type="OrderItemAuto"/>
		</order>
		<selection>
			<item xsi:type="SelectedItemAuto"/>
		</selection>
		<outputParameters/>
		<item xsi:type="StructureItemGroup">
			<groupItems>
				<item xsi:type="GroupItemField">
					<field>ЗаказПокупателя</field>
					<groupType>Items</groupType>
					<periodAdditionType>None</periodAdditionType>
					<periodAdditionBegin xsi:type="xs:dateTime">0001-01-01T00:00:00</periodAdditionBegin>
					<periodAdditionEnd xsi:type="xs:dateTime">0001-01-01T00:00:00</periodAdditionEnd>
				</item>
			</groupItems>
			<order>
				<item xsi:type="OrderItemAuto"/>
			</order>
			<selection>
				<item xsi:type="SelectedItemAuto"/>
			</selection>
			<outputParameters/>
			<item xsi:type="StructureItemGroup">
				<groupItems>
					<item xsi:type="GroupItemField">
						<field>Продукция</field>
						<groupType>Items</groupType>
						<periodAdditionType>None</periodAdditionType>
						<periodAdditionBegin xsi:type="xs:dateTime">0001-01-01T00:00:00</periodAdditionBegin>
						<periodAdditionEnd xsi:type="xs:dateTime">0001-01-01T00:00:00</periodAdditionEnd>
					</item>
					<item xsi:type="GroupItemField">
						<field>ХарактеристикаПродукции</field>
						<groupType>Items</groupType>
						<periodAdditionType>None</periodAdditionType>
						<periodAdditionBegin xsi:type="xs:dateTime">0001-01-01T00:00:00</periodAdditionBegin>
						<periodAdditionEnd xsi:type="xs:dateTime">0001-01-01T00:00:00</periodAdditionEnd>
					</item>
				</groupItems>
				<order>
					<item xsi:type="OrderItemAuto"/>
				</order>
				<selection>
					<item xsi:type="SelectedItemAuto"/>
				</selection>
				<outputParameters/>
			</item>
		</item>
	</item>
</Settings>﻿<?xml version="1.0" encoding="UTF-8"?>
<SchemaFile xmlns="" xmlns:xs="http://www.w3.org/2001/XMLSchema" xmlns:xsi="http://www.w3.org/2001/XMLSchema-instance">
	<dataCompositionSchema xmlns="http://v8.1c.ru/8.1/data-composition-system/schema"/>
</SchemaFile>